{
    "playlist_info": {
        "name": "「欧美live」听全场的热闹驱散一个人的孤独",
        "trackcount": 86,
        "playcount": 527086,
        "creator": "URmykryptonite",
        "createDate": "2016-10-06",
        "heat": 206.0
    },
    "songs": [
        {
            "name": "Radioactive",
            "artist": "Imagine Dragons",
            "id": 28283972
        },
        {
            "name": "Demons",
            "artist": "Imagine Dragons",
            "id": 28283979
        },
        {
            "name": "Demons (Acoustic Live In London)",
            "artist": "Imagine Dragons",
            "id": 28264547
        },
        {
            "name": "It's Time",
            "artist": "Imagine Dragons",
            "id": 28283981
        },
        {
            "name": "It's Time (Live)",
            "artist": "Imagine Dragons",
            "id": 27916123
        },
        {
            "name": "Stand By Me (2015 Billboard Music Awards)",
            "artist": "Imagine Dragons",
            "id": 33678730
        },
        {
            "name": "Shots (Acoustic (Piano) / Live From The Smith Center / Las Vegas / 2015)",
            "artist": "Imagine Dragons",
            "id": 31789012
        },
        {
            "name": "Blank Space (Imagine Dragons Cover)",
            "artist": "Imagine Dragons",
            "id": 31356043
        },
        {
            "name": "Viva La Vida (Live in Paris, 2008)",
            "artist": "Coldplay",
            "id": 3985869
        },
        {
            "name": "Yellow (Live)",
            "artist": "Coldplay",
            "id": 26830942
        },
        {
            "name": "Paradise (Live)",
            "artist": "Coldplay",
            "id": 26830948
        },
        {
            "name": "The Scientist (Live)",
            "artist": "Coldplay",
            "id": 30398912
        },
        {
            "name": "Fix You (Live)",
            "artist": "Coldplay",
            "id": 26830951
        },
        {
            "name": "A Sky Full of Stars (Live at the Royal Albert Hall, London)",
            "artist": "Coldplay",
            "id": 29750379
        },
        {
            "name": "Strawberry Swing (Live in Madrid, 2008)",
            "artist": "Coldplay",
            "id": 3985865
        },
        {
            "name": "Glass of Water (Live in Sydney, 2009)",
            "artist": "Coldplay",
            "id": 3985856
        },
        {
            "name": "Death and All His Friends (Live in Madrid, 2008)",
            "artist": "Coldplay",
            "id": 3985878
        },
        {
            "name": "Hotel California (Live)",
            "artist": "Eagles",
            "id": 5264302
        },
        {
            "name": "Zombie (Live)",
            "artist": "The Cranberries",
            "id": 4329963
        },
        {
            "name": "What Makes You Beautiful (Live)",
            "artist": "One Direction",
            "id": 4232604
        },
        {
            "name": "Kiss You (Live Version From The Motion Picture \"One Direction: This Is Us\")",
            "artist": "One Direction",
            "id": 27485089
        },
        {
            "name": "Rock Me (Live Version from The Motion Picture \"One Direction: This Is Us\")",
            "artist": "One Direction",
            "id": 28288644
        },
        {
            "name": "Up All Night (Live)",
            "artist": "One Direction",
            "id": 4232607
        },
        {
            "name": "One Thing (Live)",
            "artist": "One Direction",
            "id": 36621023
        },
        {
            "name": "Story of My Life (Live X Factor Performance)",
            "artist": "One Direction",
            "id": 28288643
        },
        {
            "name": "Teenage Dirtbag (live)",
            "artist": "One Direction",
            "id": 34586301
        },
        {
            "name": "I Gotta Feeling / Stereo Hearts",
            "artist": "One Direction",
            "id": 26916673
        },
        {
            "name": "21 Guns(Live at the Grammy)",
            "artist": "Green Day",
            "id": 35331075
        },
        {
            "name": "21 Guns (Live at Shoreline Amphitheatre, Mountain View, CA, 9/4/10)",
            "artist": "Green Day",
            "id": 18126591
        },
        {
            "name": "Holiday (Live at Dublin, Ireland)",
            "artist": "Green Day",
            "id": 18126572
        },
        {
            "name": "Wake Me up When September Ends (Live at Nova Rock Festival, Nickelsdorf, Austria, 6/12/10)",
            "artist": "Green Day",
            "id": 18126742
        },
        {
            "name": "Apologize(live)",
            "artist": "OneRepublic",
            "id": 4224493
        },
        {
            "name": "All We Are (Live @ The Orange Lounge)",
            "artist": "OneRepublic",
            "id": 40140155
        },
        {
            "name": "Sing (Live @ 1LIVE Radiokonzert)",
            "artist": "Ed Sheeran",
            "id": 29600360
        },
        {
            "name": "The A Team (Live)",
            "artist": "Ed Sheeran",
            "id": 27514911
        },
        {
            "name": "You Need Me, I Don't Need You (Live)",
            "artist": "Ed Sheeran",
            "id": 27514915
        },
        {
            "name": "Wake Me Up (Live at the Bedford)",
            "artist": "Ed Sheeran",
            "id": 17565973
        },
        {
            "name": "Halo (Live)",
            "artist": "Beyoncé",
            "id": 28080873
        },
        {
            "name": "If I Were A Boy/You Oughta Know (Live)",
            "artist": "Beyoncé",
            "id": 2187848
        },
        {
            "name": "All too well (现场版)",
            "artist": "Taylor Swift",
            "id": 33789225
        },
        {
            "name": "Red (2013 CMA Awards Performance) [feat. Alison Krauss, Edgar Meyer, Eric Darken, Sam Bush & Vince Gill]",
            "artist": "Taylor Swift",
            "id": 27949353
        },
        {
            "name": "Drops Of Jupiter (Live/2011)",
            "artist": "Taylor Swift",
            "id": 538871098
        },
        {
            "name": "My Songs Know What You Did In The Dark (2013'S VSFS PERFORMANCE)",
            "artist": "Fall Out Boy",
            "id": 34834242
        },
        {
            "name": "Umbrella (live)",
            "artist": "Taylor Swift",
            "id": 2002270
        },
        {
            "name": "Viva La Vida",
            "artist": "Taylor Swift",
            "id": 27984002
        },
        {
            "name": "My Happy Ending (Live)",
            "artist": "Avril Lavigne",
            "id": 2117309
        },
        {
            "name": "My Happy Ending (Live Acoustic Version)",
            "artist": "Avril Lavigne",
            "id": 2117841
        },
        {
            "name": "Tik Tok (Live)",
            "artist": "Avril Lavigne",
            "id": 25657492
        },
        {
            "name": "Girlfriend (MSN Control Room)",
            "artist": "Avril Lavigne",
            "id": 16432060
        },
        {
            "name": "Kiss Me(Live)",
            "artist": "Avril Lavigne",
            "id": 34248310
        },
        {
            "name": "Better Man (Live At Knebworth)",
            "artist": "Robbie Williams",
            "id": 21524328
        },
        {
            "name": "Price Tag (feat. Chip) [Live]",
            "artist": "Jessie J",
            "id": 26524272
        },
        {
            "name": "I Gotta Feeling",
            "artist": "Tom Jones",
            "id": 38018934
        },
        {
            "name": "It's My Party (Live)",
            "artist": "Jessie J",
            "id": 27916116
        },
        {
            "name": "Masterpiece(Live)",
            "artist": "Jessie J",
            "id": 29897472
        },
        {
            "name": "Orange Colored Sky (Live from \"A Very Gaga Thanksgiving'\")",
            "artist": "Lady Gaga",
            "id": 21038577
        },
        {
            "name": "Acoustic (Captivated) [Live Version]",
            "artist": "Lady Gaga",
            "id": 28253111
        },
        {
            "name": "We Will Rock You (Live Version)",
            "artist": "Queen",
            "id": 26771441
        },
        {
            "name": "Rolling In The Deep (Live)",
            "artist": "Linkin Park",
            "id": 4152078
        },
        {
            "name": "Hall of Fame (Live in Tokyo)",
            "artist": "The Script",
            "id": 31594169
        },
        {
            "name": "Superheroes (Live in Tokyo)",
            "artist": "The Script",
            "id": 31594154
        },
        {
            "name": "Nothing On You (solo live)",
            "artist": "Bruno Mars",
            "id": 28577165
        },
        {
            "name": "Hero (Live)",
            "artist": "Mariah Carey",
            "id": 27149853
        },
        {
            "name": "Good Time (Live)",
            "artist": "Carly Rae Jepsen",
            "id": 27916126
        },
        {
            "name": "Radioactive (Live)",
            "artist": "Rita Ora",
            "id": 27916124
        },
        {
            "name": "Anything Could Happen (Live)",
            "artist": "Fun.",
            "id": 27916122
        },
        {
            "name": "Talk Dirty (Live)",
            "artist": "Jason Derulo",
            "id": 27916115
        },
        {
            "name": "Mirrors (Live)",
            "artist": "Ellie Goulding",
            "id": 27916103
        },
        {
            "name": "La La La (feat. Sam Smith) [Live]",
            "artist": "Naughty Boy",
            "id": 27916102
        },
        {
            "name": "Riot(Live)",
            "artist": "Rascal Flatts",
            "id": 31594021
        },
        {
            "name": "It's A Man's World(Live)",
            "artist": "Christina Aguilera",
            "id": 29769215
        },
        {
            "name": "Viva La Vida(Live)",
            "artist": "Westlife",
            "id": 31191363
        },
        {
            "name": "Harsh light(Live)",
            "artist": "Fun.",
            "id": 31460080
        },
        {
            "name": "Great Balls of Fire",
            "artist": "Tilman",
            "id": 403711369
        },
        {
            "name": "Dear Boy (live)",
            "artist": "Avicii",
            "id": 32648355
        },
        {
            "name": "Lay Me Down (翻唱)",
            "artist": "Hozier",
            "id": 34468031
        },
        {
            "name": "Greatest Love Of All (live)",
            "artist": "Céline Dion",
            "id": 29848587
        },
        {
            "name": "Problem & Break Free & Love Me Harder(现场版)",
            "artist": "Ariana Grande",
            "id": 29922052
        },
        {
            "name": "I Knew You Were Trouble  (现场版)",
            "artist": "Selena Gomez & The Scene",
            "id": 33987267
        },
        {
            "name": "Bubbly (Live)",
            "artist": "Colbie Caillat",
            "id": 2308053
        },
        {
            "name": "Black Magic",
            "artist": "Little Mix",
            "id": 36103667
        },
        {
            "name": "Sing / Shake It Off / Uptown Funk (Medley) (Originally by Ed Sheeran / Taylor Swift / Mark Ronson feat. Bruno Mars)",
            "artist": "Kodaline",
            "id": 36103679
        },
        {
            "name": "Married With Children",
            "artist": "Noel Gallagher",
            "id": 1789208
        },
        {
            "name": "Somewhere Only We Know (Live)",
            "artist": "Keane",
            "id": 27097706
        },
        {
            "name": "To Be With You [Live in Tokyo, Japan, February 5, 2002]",
            "artist": "Mr. Big",
            "id": 1698463
        },
        {
            "name": "for him (Live)",
            "artist": "Troye Sivan",
            "id": 419254976
        }
    ]
}