{
    "playlist_info": {
        "name": "怀旧随身听 回到悸动的90年代",
        "trackcount": 42,
        "playcount": 13973842,
        "creator": "西柚甜",
        "createDate": "2020-01-09",
        "heat": 11025.0
    },
    "songs": [
        {
            "name": "Last Dance",
            "artist": "伍佰 & China Blue",
            "id": 157276
        },
        {
            "name": "拥抱",
            "artist": "五月天",
            "id": 386927
        },
        {
            "name": "给你们",
            "artist": "张宇",
            "id": 190499
        },
        {
            "name": "New Boy",
            "artist": "朴树",
            "id": 139371
        },
        {
            "name": "小镇姑娘",
            "artist": "陶喆",
            "id": 150619
        },
        {
            "name": "闷",
            "artist": "王菲",
            "id": 300058
        },
        {
            "name": "秘密",
            "artist": "张震岳",
            "id": 543656128
        },
        {
            "name": "明天",
            "artist": "杨乃文",
            "id": 316117
        },
        {
            "name": "真的吗",
            "artist": "莫文蔚",
            "id": 277802
        },
        {
            "name": "制造浪漫",
            "artist": "陈慧琳",
            "id": 215678
        },
        {
            "name": "失恋阵线联盟",
            "artist": "草蜢",
            "id": 349892
        },
        {
            "name": "把耳朵叫醒",
            "artist": "金海心",
            "id": 247873
        },
        {
            "name": "很爱很爱你",
            "artist": "刘若英",
            "id": 254589
        },
        {
            "name": "微凉的你",
            "artist": "陈绮贞",
            "id": 209528
        },
        {
            "name": "胆小鬼",
            "artist": "梁咏琪",
            "id": 255907
        },
        {
            "name": "静止",
            "artist": "花儿乐队",
            "id": 357424
        },
        {
            "name": "真的爱你",
            "artist": "Beyond",
            "id": 346075
        },
        {
            "name": "突然想起你",
            "artist": "萧亚轩",
            "id": 307679
        },
        {
            "name": "怪你过份美丽",
            "artist": "张国荣",
            "id": 29343374
        },
        {
            "name": "雨蝶",
            "artist": "李翊君",
            "id": 258235
        },
        {
            "name": "红日",
            "artist": "李克勤",
            "id": 115502
        },
        {
            "name": "夏日倾情",
            "artist": "黎明",
            "id": 114037
        },
        {
            "name": "如果云知道",
            "artist": "许茹芸",
            "id": 307514
        },
        {
            "name": "对你爱不完",
            "artist": "郭富城",
            "id": 89805
        },
        {
            "name": "十七岁的雨季",
            "artist": "林志颖",
            "id": 114442
        },
        {
            "name": "爱你一万年 (Live)",
            "artist": "刘德华",
            "id": 29723035
        },
        {
            "name": "我要我们在一起",
            "artist": "范晓萱",
            "id": 400581333
        },
        {
            "name": "想你的365天",
            "artist": "李玟",
            "id": 106368
        },
        {
            "name": "新不了情",
            "artist": "万芳",
            "id": 298456
        },
        {
            "name": "飞机场的10:30",
            "artist": "陶喆",
            "id": 150651
        },
        {
            "name": "一路上有你",
            "artist": "张学友",
            "id": 188071
        },
        {
            "name": "护花使者",
            "artist": "李克勤",
            "id": 115569
        },
        {
            "name": "模范情书",
            "artist": "老狼",
            "id": 85562
        },
        {
            "name": "袖手旁观",
            "artist": "江美琪",
            "id": 247691
        },
        {
            "name": "爱",
            "artist": "小虎队",
            "id": 387948
        },
        {
            "name": "花",
            "artist": "花儿乐队",
            "id": 357421
        },
        {
            "name": "夏夜晚风",
            "artist": "伍佰 & China Blue",
            "id": 157263
        },
        {
            "name": "为你我受冷风吹",
            "artist": "林忆莲",
            "id": 257098
        },
        {
            "name": "今夜你会不会来",
            "artist": "黎明",
            "id": 115250
        },
        {
            "name": "这些年来",
            "artist": "张国荣",
            "id": 187775
        },
        {
            "name": "自作多情",
            "artist": "周慧敏",
            "id": 330107
        },
        {
            "name": "相约一九九八",
            "artist": "那英",
            "id": 5272610
        }
    ]
}