{
    "playlist_info": {
        "name": "欧美｜悦耳琴声邂逅温柔男声",
        "trackcount": 20,
        "playcount": 2213312,
        "creator": "赋魅",
        "createDate": "2016-07-28",
        "heat": 874.0
    },
    "songs": [
        {
            "name": "Pieces (Radio Mix)",
            "artist": "Rob Thomas",
            "id": 417953202
        },
        {
            "name": "Two Is Better Than One (Boys Like Girls Ft. Taylor Swift Acoustic Cover)",
            "artist": "Gavin Mikhail",
            "id": 1420563
        },
        {
            "name": "Any other world",
            "artist": "MIKA",
            "id": 27965288
        },
        {
            "name": "Never Again",
            "artist": "Justin Timberlake",
            "id": 18672619
        },
        {
            "name": "All By Myself",
            "artist": "Eric Carmen",
            "id": 5048584
        },
        {
            "name": "Chasing Cars",
            "artist": "Snow Patrol",
            "id": 21730832
        },
        {
            "name": "Hands On Deck",
            "artist": "Waking Ashland",
            "id": 22359596
        },
        {
            "name": "The Scientist",
            "artist": "Coldplay",
            "id": 17177367
        },
        {
            "name": "Make You Feel My Love",
            "artist": "Ronan Keating",
            "id": 18548987
        },
        {
            "name": "Boston",
            "artist": "Augustana",
            "id": 3879945
        },
        {
            "name": "Balloons",
            "artist": "The Orange Lights",
            "id": 2006212
        },
        {
            "name": "Safe in My Hands",
            "artist": "Eli Lieb",
            "id": 28762607
        },
        {
            "name": "Don't Miss Now",
            "artist": "Downhere",
            "id": 22599297
        },
        {
            "name": "Invisible",
            "artist": "Hunter Hayes",
            "id": 28290523
        },
        {
            "name": "Relief",
            "artist": "Chris Garneau",
            "id": 1141597
        },
        {
            "name": "FOOLS",
            "artist": "Troye Sivan",
            "id": 34383213
        },
        {
            "name": "All of the Stars",
            "artist": "Ed Sheeran",
            "id": 28566204
        },
        {
            "name": "Iridescent (Version 2)",
            "artist": "Linkin Park",
            "id": 16686618
        },
        {
            "name": "Something To Say",
            "artist": "Starfield",
            "id": 22592070
        },
        {
            "name": "Sound of a Broken Heart",
            "artist": "Westlife",
            "id": 20707433
        }
    ]
}