{
    "playlist_info": {
        "name": "每天像盛花热烈，像晨早清白，万物晴朗",
        "trackcount": 36,
        "playcount": 12212,
        "creator": "模嗯嗯",
        "createDate": "2021-06-27",
        "heat": 16.0
    },
    "songs": [
        {
            "name": "满载樱花的列车开往春天",
            "artist": "温野",
            "id": 1435225104
        },
        {
            "name": "不管什么天气，记得随时带上自己的阳光",
            "artist": "Hea2t",
            "id": 1334861358
        },
        {
            "name": "我都快忘了你笑起来的时候有多美",
            "artist": "陈嘉俊是这个嘉",
            "id": 1333049915
        },
        {
            "name": "最幸福的事，就是在喜欢你的每一天里，被你喜欢",
            "artist": "Hea2t",
            "id": 1345022048
        },
        {
            "name": "西边有朵像你的云",
            "artist": "紫夜黑海",
            "id": 495172525
        },
        {
            "name": "用羽毛织出一条淡蓝色的小径",
            "artist": "Cicada",
            "id": 350141
        },
        {
            "name": "我们在黄昏的树荫下出发，走到朝阳的尽头，绕过绿色的岛，穿越溪上的石桥和杂乱的铺子小巷，走进栅栏围拢的花园里，你忽然低头跑开，这时我才缓过神看你，好像你我初初相遇",
            "artist": "岸生",
            "id": 519704673
        },
        {
            "name": "原来每束光真的会经过你的脸庞",
            "artist": "Eunomia",
            "id": 472657243
        },
        {
            "name": "有一只小鸟飞到了我家窗外的树稍上",
            "artist": "Grand",
            "id": 474668315
        },
        {
            "name": "柠檬水的香气和夏天的风.",
            "artist": "YoliBaby",
            "id": 1406259632
        },
        {
            "name": "和煦的糖果风",
            "artist": "Candy_Wind",
            "id": 439142564
        },
        {
            "name": "所 有 的 美 好 終 會 相 互 奔 赴",
            "artist": "bbbluelee",
            "id": 1808327709
        },
        {
            "name": "所念皆星河，山海皆可平",
            "artist": "白谭",
            "id": 1407583299
        },
        {
            "name": "花和你",
            "artist": "CMJ",
            "id": 1356157853
        },
        {
            "name": "你是落日弥漫的橘，天边透亮的星",
            "artist": "Hea2t",
            "id": 1463366813
        },
        {
            "name": "柠檬树下",
            "artist": "dylanf",
            "id": 1351936553
        },
        {
            "name": "在你身边",
            "artist": "九月橙",
            "id": 492219052
        },
        {
            "name": "天微雨，她就像朵莲花，开满我全部的视线。",
            "artist": "十指流玉",
            "id": 524805604
        },
        {
            "name": "繁花落",
            "artist": "风吹心散",
            "id": 1336600547
        },
        {
            "name": "曙光",
            "artist": "四季音色",
            "id": 1315824155
        },
        {
            "name": "荷灯",
            "artist": "钱晨航",
            "id": 494476060
        },
        {
            "name": "起手探星河",
            "artist": "Otanmine",
            "id": 1812258351
        },
        {
            "name": "丛林之悦",
            "artist": "阿铭",
            "id": 452733123
        },
        {
            "name": "风起的时候",
            "artist": "佚名",
            "id": 863682051
        },
        {
            "name": "莲有秀兮",
            "artist": "饭碗的彼岸",
            "id": 866032176
        },
        {
            "name": "花梦旅人",
            "artist": "世间满樱花",
            "id": 427017519
        },
        {
            "name": "柠檬汽水",
            "artist": "钱晨航",
            "id": 479374667
        },
        {
            "name": "做你独家宇宙",
            "artist": "轻墨安源",
            "id": 554974969
        },
        {
            "name": "夜落樱花",
            "artist": "WR-锐",
            "id": 1433256350
        },
        {
            "name": "风摇盛夏",
            "artist": "逆时针向",
            "id": 1843577172
        },
        {
            "name": "我们点燃来时的路 撑着我们继续向前行走",
            "artist": "Yzz",
            "id": 1830161248
        },
        {
            "name": "夏新晨",
            "artist": "逆时针向",
            "id": 487089933
        },
        {
            "name": "人间风景",
            "artist": "忘乡",
            "id": 1454884913
        },
        {
            "name": "森林",
            "artist": "灰澈",
            "id": 495562302
        },
        {
            "name": "薄荷绿",
            "artist": "逆时针向",
            "id": 1483533107
        },
        {
            "name": "In The Good Times",
            "artist": "忘乡",
            "id": 515715891
        }
    ]
}