{
    "playlist_info": {
        "name": "猫的树OST-想你/飞奔/见面/可爱",
        "trackcount": 32,
        "playcount": 284,
        "creator": "今天也开心s",
        "createDate": "2023-06-13",
        "heat": 18.0
    },
    "songs": [
        {
            "name": "路过你的青春",
            "artist": "歌之初乐队",
            "id": 1402051900
        },
        {
            "name": "你是不是也想和我一起走走",
            "artist": "尹露浠",
            "id": 2056204117
        },
        {
            "name": "轻轻的夏天",
            "artist": "尹露浠",
            "id": 2056203125
        },
        {
            "name": "当我奔向你",
            "artist": "林晨阳",
            "id": 2056203124
        },
        {
            "name": "我想我会",
            "artist": "尹露浠",
            "id": 2056203126
        },
        {
            "name": "情话贩卖机",
            "artist": "Gonaki",
            "id": 1480088792
        },
        {
            "name": "毕业留言",
            "artist": "孟凡明",
            "id": 1861640513
        },
        {
            "name": "Found What I've Been Looking For",
            "artist": "SATV Music",
            "id": 1444339045
        },
        {
            "name": "耳 喃",
            "artist": "PIggy",
            "id": 1803936748
        },
        {
            "name": "April Encounter",
            "artist": "很美味",
            "id": 551400874
        },
        {
            "name": "Dear You",
            "artist": "昨夜派对（L.N Party）",
            "id": 1812175842
        },
        {
            "name": "去见你",
            "artist": "徐秉龙",
            "id": 1354629987
        },
        {
            "name": "少年",
            "artist": "PIggy",
            "id": 1979981796
        },
        {
            "name": "粉色苏打",
            "artist": "安全着陆",
            "id": 1309833126
        },
        {
            "name": "心动贩卖机",
            "artist": "PIggy",
            "id": 1433413470
        },
        {
            "name": "December Composer (Piano Version)",
            "artist": "Vicky宣宣",
            "id": 1805801737
        },
        {
            "name": "可以吗",
            "artist": "王嘉懿",
            "id": 1979981795
        },
        {
            "name": "笨蛋",
            "artist": "徐秉龙",
            "id": 1397680229
        },
        {
            "name": "Turns",
            "artist": "Lionzed",
            "id": 1486316620
        },
        {
            "name": "My girl",
            "artist": "Gonaki",
            "id": 1937736041
        },
        {
            "name": "泛滥",
            "artist": "Gonaki",
            "id": 1937732365
        },
        {
            "name": "A Sad Me In Your Eyes",
            "artist": "昨夜派对（L.N Party）",
            "id": 1404709472
        },
        {
            "name": "明天可以见到你吗？（电视剧《如此可爱的我们》插曲）",
            "artist": "坤木Joymo",
            "id": 1403626834
        },
        {
            "name": "星上人",
            "artist": "陆杰awr",
            "id": 1467201259
        },
        {
            "name": "如此可爱的我们",
            "artist": "阎其儿Jill",
            "id": 1467201248
        },
        {
            "name": "圈住你",
            "artist": "一口甜",
            "id": 1372552573
        },
        {
            "name": "遇见克莱因蓝",
            "artist": "章熙梦Dream",
            "id": 1886715284
        },
        {
            "name": "与你共赴",
            "artist": "很美味",
            "id": 1920051173
        },
        {
            "name": "Before",
            "artist": "李学仕",
            "id": 1875254487
        },
        {
            "name": "佩奇的夏天",
            "artist": "阁楼演奏班",
            "id": 1381814876
        },
        {
            "name": "We",
            "artist": "酸月亮 Sour Moon",
            "id": 1860879623
        },
        {
            "name": "夏夜露天电影(Summer Night Open-Air Movie)",
            "artist": "白色海岸The White Coast",
            "id": 1948694170
        }
    ]
}